True_Tiktok_Uploader/__init__.py
True_Tiktok_Uploader/auth.py
True_Tiktok_Uploader/config.py
True_Tiktok_Uploader/upload.py
true_tiktok_uploader-2026.1.7.3.dist-info/METADATA
true_tiktok_uploader-2026.1.7.3.dist-info/WHEEL
true_tiktok_uploader-2026.1.7.3.dist-info/licenses/LICENCE
true_tiktok_uploader-2026.1.7.3.dist-info/RECORD
