Metadata-Version: 2.4
Name: True_Tiktok_Uploader
Version: 2026.1.7.3
Summary: an automated, selenium based tiktok video uploader.
Author: TrueGIXERJ
License-Expression: GPL-3.0-only
License-File: LICENCE
Classifier: Operating System :: Microsoft :: Windows
Classifier: Programming Language :: Python :: 3
Requires-Python: >=3.12
Requires-Dist: selenium
Requires-Dist: truegixerj-utils
